full_alchemyst/__init__.py
full_alchemyst/full_alchemyst.py
full_alchemyst/showcase.py
full_alchemyst-1.0.1.dist-info/LICENSE
full_alchemyst-1.0.1.dist-info/METADATA
full_alchemyst-1.0.1.dist-info/WHEEL
full_alchemyst-1.0.1.dist-info/top_level.txt
full_alchemyst-1.0.1.dist-info/RECORD
